{"cameraMode":{"drawMode":0,"name":"Shaded","section":"Shading Mode"},"sceneLighting":true,"audioPlay":false,"sceneViewState":{"showFog":true,"showMaterialUpdate":false,"showSkybox":true,"showFlares":true,"showImageEffects":true,"showParticleSystems":true},"in2DMode":false,"pivot":{"x":-2.9973044395446779,"y":-0.32282447814941409,"z":13.397911071777344},"rotation":{"x":-0.12708620727062226,"y":0.38396742939949038,"z":-0.053453050553798679,"w":-0.9130056500434876},"size":7.181375503540039,"orthographic":false}